simulation_smpl/__init__.py
simulation_smpl/smpl.py
simulation_smpl-1.0.3.dist-info/LICENSE
simulation_smpl-1.0.3.dist-info/METADATA
simulation_smpl-1.0.3.dist-info/WHEEL
simulation_smpl-1.0.3.dist-info/top_level.txt
simulation_smpl-1.0.3.dist-info/RECORD
