Metadata-Version: 2.1
Name: simulation-smpl
Version: 1.0.3
Summary: A Python implementation of the discrete event simulation environment 'smpl' (original C version by Myron H. MacDougall)
Home-page: UNKNOWN
License: MIT
Project-URL: Bug Tracker, https://github.com/fontoura/smpl-Python/issues
Project-URL: Source Code, https://github.com/fontoura/smpl-Python
Keywords: simulation,smpl
Platform: UNKNOWN
License-File: LICENSE
